ghreq/__init__.py
ghreq/py.typed
ghreq-0.6.0.dist-info/METADATA
ghreq-0.6.0.dist-info/WHEEL
ghreq-0.6.0.dist-info/licenses/LICENSE
ghreq-0.6.0.dist-info/RECORD
