Metadata-Version: 2.4
Name: ghreq
Version: 0.6.0
Summary: Minimal and opinionated GitHub API client
Project-URL: Source Code, https://github.com/jwodder/ghreq
Project-URL: Bug Tracker, https://github.com/jwodder/ghreq/issues
Author-email: John Thorvald Wodder II <ghreq@varonathe.org>
License-Expression: MIT
License-File: LICENSE
Keywords: GitHub,GitHub API,GitHub REST API,REST API client
Classifier: Intended Audience :: Developers
Classifier: Programming Language :: Python :: 3
Classifier: Programming Language :: Python :: 3 :: Only
Classifier: Programming Language :: Python :: 3.10
Classifier: Programming Language :: Python :: 3.11
Classifier: Programming Language :: Python :: 3.12
Classifier: Programming Language :: Python :: 3.13
Classifier: Programming Language :: Python :: 3.14
Classifier: Programming Language :: Python :: Implementation :: CPython
Classifier: Programming Language :: Python :: Implementation :: PyPy
Classifier: Topic :: Internet :: WWW/HTTP
Classifier: Typing :: Typed
Requires-Python: >=3.10
Requires-Dist: requests~=2.20
